samvaad/__init__.py
samvaad/interfaces/api.py
samvaad/interfaces/cli.py
samvaad/pipeline/__init__.py
samvaad/pipeline/deletion/__init__.py
samvaad/pipeline/deletion/deletion.py
samvaad/pipeline/generation/__init__.py
samvaad/pipeline/generation/generation.py
samvaad/pipeline/generation/kokoro_tts.py
samvaad/pipeline/ingestion/__init__.py
samvaad/pipeline/ingestion/chunking.py
samvaad/pipeline/ingestion/embedding.py
samvaad/pipeline/ingestion/ingestion.py
samvaad/pipeline/ingestion/preprocessing.py
samvaad/pipeline/retrieval/__init__.py
samvaad/pipeline/retrieval/query.py
samvaad/pipeline/retrieval/voice_mode.py
samvaad/pipeline/vectorstore/__init__.py
samvaad/pipeline/vectorstore/vectorstore.py
samvaad/utils/__init__.py
samvaad/utils/clean_markdown.py
samvaad/utils/filehash_db.py
samvaad/utils/gpu_utils.py
samvaad/utils/hashing.py
samvaad-0.1.0.dist-info/licenses/LICENSE
samvaad-0.1.0.dist-info/METADATA
samvaad-0.1.0.dist-info/WHEEL
samvaad-0.1.0.dist-info/entry_points.txt
samvaad-0.1.0.dist-info/top_level.txt
samvaad-0.1.0.dist-info/RECORD
