Metadata-Version: 2.4
Name: samvaad
Version: 0.1.0
Summary: An AI-powered conversational assistant with voice support and document intelligence
Author-email: Atharva Verma <atharva.verma18@gmail.com>
License-Expression: MIT
Project-URL: Homepage, https://github.com/atharva-again/samvaad
Project-URL: Repository, https://github.com/atharva-again/samvaad
Project-URL: Issues, https://github.com/atharva-again/samvaad/issues
Classifier: Development Status :: 3 - Alpha
Classifier: Intended Audience :: Developers
Classifier: Topic :: Scientific/Engineering :: Artificial Intelligence
Classifier: Programming Language :: Python :: 3
Classifier: Programming Language :: Python :: 3.8
Classifier: Programming Language :: Python :: 3.9
Classifier: Programming Language :: Python :: 3.10
Classifier: Programming Language :: Python :: 3.11
Requires-Python: >=3.8
License-File: LICENSE
Requires-Dist: rich>=13.0.0
Requires-Dist: click>=8.0.4
Requires-Dist: python-dotenv>=1.1.1
Requires-Dist: prompt-toolkit>=3.0.0
Requires-Dist: psutil>=6.1.0
Requires-Dist: fastapi>=0.116.1
Requires-Dist: uvicorn>=0.35.0
Requires-Dist: python-multipart>=0.0.20
Requires-Dist: chromadb>=1.0.20
Requires-Dist: openai>=1.106.0
Requires-Dist: sentence-transformers>=5.1.0
Requires-Dist: tiktoken>=0.11.0
Requires-Dist: google-genai>=1.36.0
Requires-Dist: docling>=2.53.0
Requires-Dist: beautifulsoup4>=4.13.5
Requires-Dist: requests>=2.32.5
Requires-Dist: rank-bm25>=0.2.2
Requires-Dist: faster-whisper>=1.2.0
Requires-Dist: sounddevice>=0.4.7
Requires-Dist: webrtcvad>=2.0.10
Requires-Dist: kokoro>=0.9.4
Requires-Dist: kokoro-onnx>=0.3.1
Requires-Dist: transformers
Requires-Dist: tokenizers
Requires-Dist: pytest>=8.3.3
Requires-Dist: pytest-mock>=3.14.0
Provides-Extra: dev
Requires-Dist: pytest>=8.3.3; extra == "dev"
Requires-Dist: pytest-mock>=3.14.0; extra == "dev"
Requires-Dist: pytest-cov>=4.1.0; extra == "dev"
Requires-Dist: black>=23.0.0; extra == "dev"
Requires-Dist: isort>=5.12.0; extra == "dev"
Requires-Dist: flake8>=6.0.0; extra == "dev"
Requires-Dist: mypy>=1.5.0; extra == "dev"
Requires-Dist: pre-commit>=3.5.0; extra == "dev"
Provides-Extra: cpu
Requires-Dist: torch; extra == "cpu"
Provides-Extra: gpu
Requires-Dist: torch[cu121]; extra == "gpu"
Provides-Extra: voice
Requires-Dist: sounddevice>=0.4.7; extra == "voice"
Requires-Dist: webrtcvad>=2.0.10; extra == "voice"
Requires-Dist: kokoro>=0.9.4; extra == "voice"
Requires-Dist: kokoro-onnx>=0.3.1; extra == "voice"
Dynamic: license-file
